{
	"info": {
		"_postman_id": "e11ccb77-c61e-4476-8880-c87c10a0d0c6",
		"name": "Minesweeper",
		"schema": "https://schema.getpostman.com/json/collection/v2.1.0/collection.json",
		"_exporter_id": "1934421"
	},
	"item": [
		{
			"name": "New Game",
			"request": {
				"method": "PUT",
				"header": [],
				"url": {
					"raw": "localhost:8080/v1/api/minesweeper/new-game",
					"host": [
						"localhost"
					],
					"port": "8080",
					"path": [
						"v1",
						"api",
						"minesweeper",
						"new-game"
					]
				}
			},
			"response": []
		},
		{
			"name": "Get Board",
			"request": {
				"method": "GET",
				"header": [],
				"url": {
					"raw": "localhost:8080/v1/api/minesweeper",
					"host": [
						"localhost"
					],
					"port": "8080",
					"path": [
						"v1",
						"api",
						"minesweeper"
					]
				}
			},
			"response": []
		},
		{
			"name": "Click",
			"request": {
				"method": "POST",
				"header": [],
				"body": {
					"mode": "raw",
					"raw": "{\n    \"x\": 0,\n    \"y\": 0\n}",
					"options": {
						"raw": {
							"language": "json"
						}
					}
				},
				"url": {
					"raw": "localhost:8080/v1/api/minesweeper/click",
					"host": [
						"localhost"
					],
					"port": "8080",
					"path": [
						"v1",
						"api",
						"minesweeper",
						"click"
					]
				}
			},
			"response": []
		},
		{
			"name": "Mark",
			"request": {
				"method": "POST",
				"header": [],
				"body": {
					"mode": "raw",
					"raw": "{\n    \"x\": 0,\n    \"y\": 0\n}",
					"options": {
						"raw": {
							"language": "json"
						}
					}
				},
				"url": {
					"raw": "localhost:8080/v1/api/minesweeper/mark",
					"host": [
						"localhost"
					],
					"port": "8080",
					"path": [
						"v1",
						"api",
						"minesweeper",
						"mark"
					]
				}
			},
			"response": []
		}
	]
}